effdim/__init__.py
effdim/_rust.cpython-314-x86_64-linux-musl.so
effdim/api.py
effdim/geometry.py
effdim/metrics.py
effdim-0.1.1.dist-info/METADATA
effdim-0.1.1.dist-info/WHEEL
effdim-0.1.1.dist-info/licenses/LICENSE
effdim.libs/libgcc_s-f685abf1.so.1
effdim-0.1.1.dist-info/RECORD
